LICENSE
README.md
setup.py
django_auto_serializer/__init__.py
django_auto_serializer/auto_serializer.py
django_auto_serializer.egg-info/PKG-INFO
django_auto_serializer.egg-info/SOURCES.txt
django_auto_serializer.egg-info/dependency_links.txt
django_auto_serializer.egg-info/requires.txt
django_auto_serializer.egg-info/top_level.txt