Metadata-Version: 2.1
Name: django-auto-serializer
Version: 0.4.2
Summary: Django app that automates objects tree serialization recursively
Home-page: https://github.com/peppelinux/django-auto-serializer
Author: Giuseppe De Marco
Author-email: giuseppe.demarco@unical.it
License: BSD
Platform: UNKNOWN
Classifier: Development Status :: 5 - Production/Stable
Classifier: License :: OSI Approved :: BSD License
Classifier: Programming Language :: Python :: 3 :: Only
